enthusiast_agent_re_act/__init__.py
enthusiast_agent_re_act/base_re_act_agent.py
enthusiast_agent_re_act/structured_re_act_output_parser.py
enthusiast_agent_re_act/template_re_act_prompt.py
enthusiast_agent_re_act-1.3.0.dist-info/METADATA
enthusiast_agent_re_act-1.3.0.dist-info/WHEEL
enthusiast_agent_re_act-1.3.0.dist-info/RECORD
